Workbook
Name aporte: Planilha1!$D$20
Name patrimonio: Planilha1!$D$23
Name qtd_anos: Planilha1!$D$21
Name rendimento_carteira: Planilha1!$D$15
Name salario: Planilha1!$D$14
Name taxa_mensal: Planilha1!$D$22

Sheet Planilha1
B13: Configurações
B14: Salário | D14: 4200
B15: Rendimento Carteira | D15: 0.6
B16: Sugestão de Investimento | D16: =salario*30% -> 1260
B19: Investimento Mensal
B20: Quanto investir por mês ? | D20: 1260
B21: Por Quantos Anos ? | D21: 10
B22: Taxa de Rendimento mensal ? | D22: 0.01079
B23: Patrimônio acumulado ? | D23: =FV(taxa_mensal,qtd_anos*12,aporte*-1) -> 306538.11
B24: Dividendos Mensais ? | D24: =patrimonio*rendimento_carteira -> 183922.86
B26: Cenários | D26: Dividendo
A27: 2 | B27: Quantos em 2 anos? | C27: =FV($D$22,A27*12,$D$20*-1) -> 34306.81 | D27: =C27*rendimento_carteira -> 20584.086
A28: 5 | B28: Quantos em 5 anos? | C28: =FV($D$22,A28*12,$D$20*-1) -> 105558.91 | D28: =C28*rendimento_carteira -> 63335.347
A29: 10 | B29: Quantos em 10 anos? | C29: =FV($D$22,A29*12,$D$20*-1) -> 306538.11 | D29: =C29*rendimento_carteira -> 183922.86
A30: 20 | B30: Quantos em 20 anos? | C30: =FV($D$22,A30*12,$D$20*-1) -> 1417750 | D30: =C30*rendimento_carteira -> 850649.99
A31: 30 | B31: Quantos em 30 anos? | C31: =FV($D$22,A31*12,$D$20*-1) -> 5445933.8 | D31: =C31*rendimento_carteira -> 3267560.3
B34: Perfil | D34: Agressivo
B35: Valor a ser investido por mês | D35: =aporte -> 1260
B37: TIPO DE FIIs | C37: Percentual Sugerido | D37: Valor
B38: Papel | C38: =VLOOKUP($D$34&"-"&B38,Planilha2!$B$4:$E$24,4,FALSE) -> 0.5 | D38: =C38*$D$35 -> 630
B39: Tijolo | C39: =VLOOKUP($D$34&"-"&B39,Planilha2!$B$4:$E$24,4,FALSE) -> 0.1 | D39: =C39*$D$35 -> 126
B40: Híbridos | C40: =VLOOKUP($D$34&"-"&B40,Planilha2!$B$4:$E$24,4,FALSE) -> 0.05 | D40: =C40*$D$35 -> 63
B41: FOFs | C41: =VLOOKUP($D$34&"-"&B41,Planilha2!$B$4:$E$24,4,FALSE) -> 0.05 | D41: =C41*$D$35 -> 63
B42: Desenvolvimento | C42: =VLOOKUP($D$34&"-"&B42,Planilha2!$B$4:$E$24,4,FALSE) -> 0.2 | D42: =C42*$D$35 -> 252
B43: Hotelarias | C43: =VLOOKUP($D$34&"-"&B43,Planilha2!$B$4:$E$24,4,FALSE) -> 0.1 | D43: =C43*$D$35 -> 126
D44: =SUM(D38:D43) -> 1260

Sheet Planilha2
B4: Chave | C4: Perfil | D4: Tipo de FII | E4: %
B5: =$C$5&"-"&D5 -> Conservador-Papel | C5: Conservador | D5: Papel | E5: 0.3
B6: =$C$5&"-"&D6 -> Conservador-Tijolo | C6: Conservador | D6: Tijolo | E6: 0.5
B7: =$C$5&"-"&D7 -> Conservador-Híbridos | C7: Conservador | D7: Híbridos | E7: 0.1
B8: =$C$5&"-"&D8 -> Conservador-FOFs | C8: Conservador | D8: FOFs | E8: 0.1
B9: =$C$5&"-"&D9 -> Conservador-Desenvolvimento | C9: Conservador | D9: Desenvolvimento | E9: 0
B10: =$C$5&"-"&D10 -> Conservador-Hotelarias | C10: Conservador | D10: Hotelarias | E10: 0
B12: =$C$12&"-"&D12 -> Moderado-Papel | C12: Moderado | D12: Papel | E12: 0.32
B13: =$C$12&"-"&D13 -> Moderado-Tijolo | C13: Moderado | D13: Tijolo | E13: 0.35
B14: =$C$12&"-"&D14 -> Moderado-Híbridos | C14: Moderado | D14: Híbridos | E14: 0.08
B15: =$C$12&"-"&D15 -> Moderado-FOFs | C15: Moderado | D15: FOFs | E15: 0.05
B16: =$C$12&"-"&D16 -> Moderado-Desenvolvimento | C16: Moderado | D16: Desenvolvimento | E16: 0.1
B17: =$C$12&"-"&D17 -> Moderado-Hotelarias | C17: Moderado | D17: Hotelarias | E17: 0.1
B19: =$C$19&"-"&D19 -> Agressivo-Papel | C19: Agressivo | D19: Papel | E19: 0.5
B20: =$C$19&"-"&D20 -> Agressivo-Tijolo | C20: Agressivo | D20: Tijolo | E20: 0.1
B21: =$C$19&"-"&D21 -> Agressivo-Híbridos | C21: Agressivo | D21: Híbridos | E21: 0.05
B22: =$C$19&"-"&D22 -> Agressivo-FOFs | C22: Agressivo | D22: FOFs | E22: 0.05
B23: =$C$19&"-"&D23 -> Agressivo-Desenvolvimento | C23: Agressivo | D23: Desenvolvimento | E23: 0.2
B24: =$C$19&"-"&D24 -> Agressivo-Hotelarias | C24: Agressivo | D24: Hotelarias | E24: 0.1
